{"song":{"player2":"dad","player1":"bf","speed":2.1,"needsVoices":false,"sectionLengths":[],"song":"Blocked","bpm":225,"sections":0,"validScore":true,"notes":[{"mustHitSection":false,"typeOfSection":0,"lengthInSteps":16,"sectionNotes":[[0,3,0],[400,3,0],[800,3,0],[1066,3,0]]},{"mustHitSection":true,"typeOfSection":0,"lengthInSteps":16,"sectionNotes":[[1466,7,0],[1866,7,0],[2133,3,0]]},{"mustHitSection":true,"typeOfSection":0,"lengthInSteps":16,"sectionNotes":[[2533,3,0],[2933,3,0]]},{"mustHitSection":true,"typeOfSection":0,"lengthInSteps":16,"sectionNotes":[[3200,3,0],[3600,3,0],[4000,3,0],[4266,6,0]]},{"mustHitSection":false,"typeOfSection":0,"lengthInSteps":16,"sectionNotes":[[4533,3,0],[4800,0,0],[5066,1,0],[5333,2,0]]},{"mustHitSection":true,"typeOfSection":0,"lengthInSteps":16,"sectionNotes":[[5600,6,0],[5866,4,0],[6133,7,0],[6400,2,0]]},{"mustHitSection":true,"typeOfSection":0,"lengthInSteps":16,"sectionNotes":[[6666,3,0],[6933,0,0],[7200,1,0],[7466,2,0]]},{"mustHitSection":true,"typeOfSection":0,"lengthInSteps":16,"sectionNotes":[[7733,2,0],[8000,0,0],[8266,3,0],[8533,7,0]]},{"mustHitSection":false,"typeOfSection":0,"lengthInSteps":16,"sectionNotes":[[8933,3,0],[9333,3,0]]},{"mustHitSection":true,"typeOfSection":0,"lengthInSteps":16,"sectionNotes":[[9600,7,0],[10000,7,0],[10400,7,0],[10666,3,0]]},{"mustHitSection":true,"typeOfSection":0,"lengthInSteps":16,"sectionNotes":[[11066,3,0],[11466,3,0],[11733,3,0]]},{"mustHitSection":true,"typeOfSection":0,"lengthInSteps":16,"sectionNotes":[[12133,3,0],[12533,3,0]]},{"mustHitSection":false,"typeOfSection":0,"lengthInSteps":16,"sectionNotes":[[12800,2,0],[13066,3,0],[13333,0,0],[13600,1,0],[13866,2,0]]},{"mustHitSection":true,"typeOfSection":0,"lengthInSteps":16,"sectionNotes":[[14133,6,0],[14400,4,0],[14666,7,0],[14933,2,0]]},{"mustHitSection":true,"typeOfSection":0,"lengthInSteps":16,"sectionNotes":[[15200,3,0],[15466,0,0],[15733,1,0]]},{"mustHitSection":true,"typeOfSection":0,"lengthInSteps":16,"sectionNotes":[[16000,2,0],[16266,2,0],[16533,0,0],[16800,3,0],[17066,7,0]]},{"mustHitSection":false,"typeOfSection":0,"lengthInSteps":16,"sectionNotes":[[17333,0,0],[17600,2,0],[17866,2,0],[18133,0,0]]},{"mustHitSection":false,"typeOfSection":0,"lengthInSteps":16,"sectionNotes":[[18400,3,0],[18666,1,0],[18933,1,0]]},{"mustHitSection":true,"typeOfSection":0,"lengthInSteps":16,"sectionNotes":[[19200,3,0],[19200,5,266],[19466,0,0],[19733,1,0],[20000,2,0],[20266,2,0]]},{"mustHitSection":true,"typeOfSection":0,"lengthInSteps":16,"sectionNotes":[[20533,2,0],[20800,3,0],[21066,2,0],[21333,1,267],[21333,4,0]]},{"mustHitSection":false,"typeOfSection":0,"lengthInSteps":16,"sectionNotes":[[21600,0,0],[21866,3,0],[22133,3,0],[22400,2,0]]},{"mustHitSection":true,"typeOfSection":0,"lengthInSteps":16,"sectionNotes":[[22666,6,0],[22933,4,0],[23200,7,0],[23466,0,0],[23466,7,267]]},{"mustHitSection":true,"typeOfSection":0,"lengthInSteps":16,"sectionNotes":[[23733,0,0],[24000,1,0],[24266,1,0],[24533,3,0]]},{"mustHitSection":true,"typeOfSection":0,"lengthInSteps":16,"sectionNotes":[[24800,3,0],[25066,0,0],[25333,3,0],[25600,7,0]]},{"mustHitSection":false,"typeOfSection":0,"lengthInSteps":16,"sectionNotes":[[25866,0,0],[26133,2,0],[26400,2,0],[26666,0,0]]},{"mustHitSection":true,"typeOfSection":0,"lengthInSteps":16,"sectionNotes":[[26933,7,0],[27200,5,0],[27466,5,0],[27733,3,0],[27733,5,267]]},{"mustHitSection":true,"typeOfSection":0,"lengthInSteps":16,"sectionNotes":[[28000,0,0],[28266,1,0],[28533,2,0],[28800,2,0]]},{"mustHitSection":true,"typeOfSection":0,"lengthInSteps":16,"sectionNotes":[[29066,2,0],[29333,3,0],[29600,2,0],[29866,1,267],[29866,4,0]]},{"mustHitSection":false,"typeOfSection":0,"lengthInSteps":16,"sectionNotes":[[30133,0,0],[30400,3,0],[30666,3,0],[30933,2,0]]},{"mustHitSection":true,"typeOfSection":0,"lengthInSteps":16,"sectionNotes":[[31200,6,0],[31466,4,0],[31733,7,0],[32000,0,0],[32000,7,266]]},{"mustHitSection":true,"typeOfSection":0,"lengthInSteps":16,"sectionNotes":[[32266,0,0],[32533,1,0],[32800,1,0],[33066,3,0]]},{"mustHitSection":true,"typeOfSection":0,"lengthInSteps":16,"sectionNotes":[[33333,3,0],[33600,0,0],[33866,3,0],[34133,7,0]]},{"mustHitSection":false,"typeOfSection":0,"lengthInSteps":16,"sectionNotes":[[34733,3,0]]},{"mustHitSection":false,"typeOfSection":0,"lengthInSteps":16,"sectionNotes":[[35333,3,0],[35733,3,0]]},{"mustHitSection":true,"typeOfSection":0,"lengthInSteps":16,"sectionNotes":[[36333,7,0],[36933,7,0],[37333,3,0]]},{"mustHitSection":true,"typeOfSection":0,"lengthInSteps":16,"sectionNotes":[[37933,3,0]]},{"mustHitSection":true,"typeOfSection":0,"lengthInSteps":16,"sectionNotes":[[38533,3,0],[38933,3,0]]},{"mustHitSection":true,"typeOfSection":0,"lengthInSteps":16,"sectionNotes":[[39533,3,0],[40133,3,0],[40533,6,0]]},{"mustHitSection":false,"typeOfSection":0,"lengthInSteps":16,"sectionNotes":[[40933,3,0],[41333,0,0]]},{"mustHitSection":false,"typeOfSection":0,"lengthInSteps":16,"sectionNotes":[[41733,1,0],[42133,0,0],[42533,0,0]]},{"mustHitSection":true,"typeOfSection":0,"lengthInSteps":16,"sectionNotes":[[42933,5,0],[43333,7,400],[43733,0,0]]},{"mustHitSection":true,"typeOfSection":0,"lengthInSteps":16,"sectionNotes":[[44133,3,0],[44533,1,0]]},{"mustHitSection":true,"typeOfSection":0,"lengthInSteps":16,"sectionNotes":[[44933,2,0],[45333,3,0],[45733,3,0]]},{"mustHitSection":true,"typeOfSection":0,"lengthInSteps":16,"sectionNotes":[[46133,0,0],[46533,1,0],[46933,7,0]]},{"mustHitSection":false,"typeOfSection":0,"lengthInSteps":16,"sectionNotes":[[47333,0,0],[47733,2,0]]},{"mustHitSection":false,"typeOfSection":0,"lengthInSteps":16,"sectionNotes":[[48133,2,0],[48533,0,0],[48933,0,0]]},{"mustHitSection":true,"typeOfSection":0,"lengthInSteps":16,"sectionNotes":[[49333,4,0],[49733,7,0],[50133,3,0]]},{"mustHitSection":true,"typeOfSection":0,"lengthInSteps":16,"sectionNotes":[[50333,5,400],[50533,0,0],[50933,1,0]]},{"mustHitSection":true,"typeOfSection":0,"lengthInSteps":16,"sectionNotes":[[51333,2,0],[51733,2,0],[52133,2,0]]},{"mustHitSection":true,"typeOfSection":0,"lengthInSteps":16,"sectionNotes":[[52533,3,0],[52933,2,0],[53333,0,400],[53333,4,0]]},{"mustHitSection":false,"typeOfSection":0,"lengthInSteps":16,"sectionNotes":[[53733,0,0],[54133,3,0]]},{"mustHitSection":false,"typeOfSection":0,"lengthInSteps":16,"sectionNotes":[[54533,3,0],[54933,1,0],[55333,1,0]]},{"mustHitSection":true,"typeOfSection":0,"lengthInSteps":16,"sectionNotes":[[55733,4,0],[56133,7,0],[56533,0,0],[56533,7,400]]},{"mustHitSection":true,"typeOfSection":0,"lengthInSteps":16,"sectionNotes":[[56933,0,0],[57333,1,0]]},{"mustHitSection":true,"typeOfSection":0,"lengthInSteps":16,"sectionNotes":[[57733,1,0],[58133,2,0],[58533,2,0]]},{"mustHitSection":true,"typeOfSection":0,"lengthInSteps":16,"sectionNotes":[[58933,0,0],[59333,3,0],[59733,7,0]]},{"mustHitSection":false,"typeOfSection":0,"lengthInSteps":16,"sectionNotes":[[60133,3,0],[60533,3,0],[60799,3,0]]},{"mustHitSection":true,"typeOfSection":0,"lengthInSteps":16,"sectionNotes":[[61199,7,0],[61599,7,0],[61866,3,0]]},{"mustHitSection":true,"typeOfSection":0,"lengthInSteps":16,"sectionNotes":[[62266,3,0],[62666,3,0],[62933,3,0]]},{"mustHitSection":true,"typeOfSection":0,"lengthInSteps":16,"sectionNotes":[[63333,3,0],[63733,3,0],[63999,6,0]]},{"mustHitSection":false,"typeOfSection":0,"lengthInSteps":16,"sectionNotes":[[64266,3,0],[64533,0,0],[64799,1,0],[65066,2,0]]},{"mustHitSection":true,"typeOfSection":0,"lengthInSteps":16,"sectionNotes":[[65333,6,0],[65599,4,0],[65866,7,0],[66133,2,0]]},{"mustHitSection":true,"typeOfSection":0,"lengthInSteps":16,"sectionNotes":[[66399,3,0],[66666,0,0],[66933,1,0],[67199,2,0]]},{"mustHitSection":true,"typeOfSection":0,"lengthInSteps":16,"sectionNotes":[[67466,2,0],[67733,0,0],[67999,3,0],[68266,7,0]]},{"mustHitSection":false,"typeOfSection":0,"lengthInSteps":16,"sectionNotes":[[68666,3,0],[69066,3,0],[69333,3,0]]},{"mustHitSection":true,"typeOfSection":0,"lengthInSteps":16,"sectionNotes":[[69733,7,0],[70133,7,0],[70399,3,0]]},{"mustHitSection":true,"typeOfSection":0,"lengthInSteps":16,"sectionNotes":[[70799,3,0],[71199,3,0],[71466,3,0]]},{"mustHitSection":true,"typeOfSection":0,"lengthInSteps":16,"sectionNotes":[[71866,3,0],[72266,3,0],[72533,6,0]]},{"mustHitSection":false,"typeOfSection":0,"lengthInSteps":16,"sectionNotes":[[72799,3,0],[73066,0,0],[73333,1,0],[73599,2,0]]},{"mustHitSection":true,"typeOfSection":0,"lengthInSteps":16,"sectionNotes":[[73866,6,0],[74133,4,0],[74399,7,0],[74666,2,0]]},{"mustHitSection":true,"typeOfSection":0,"lengthInSteps":16,"sectionNotes":[[74933,3,0],[75199,0,0],[75466,1,0],[75733,2,0]]},{"mustHitSection":true,"typeOfSection":0,"lengthInSteps":16,"sectionNotes":[[75999,2,0],[76266,0,0],[76533,3,0],[76799,7,0]]},{"mustHitSection":false,"typeOfSection":0,"lengthInSteps":16,"sectionNotes":[[77066,0,0],[77333,2,0],[77599,2,0],[77866,0,0]]},{"mustHitSection":true,"typeOfSection":0,"lengthInSteps":16,"sectionNotes":[[78133,7,0],[78399,5,0],[78666,5,0],[78933,3,0],[78933,5,266]]},{"mustHitSection":true,"typeOfSection":0,"lengthInSteps":16,"sectionNotes":[[79199,0,0],[79466,1,0],[79733,2,0],[79999,2,0]]},{"mustHitSection":true,"typeOfSection":0,"lengthInSteps":16,"sectionNotes":[[80266,2,0],[80533,3,0],[80799,2,0],[81066,1,267],[81066,4,0]]},{"mustHitSection":false,"typeOfSection":0,"lengthInSteps":16,"sectionNotes":[[81333,0,0],[81599,3,0],[81866,3,0],[82133,2,0]]},{"mustHitSection":true,"typeOfSection":0,"lengthInSteps":16,"sectionNotes":[[82399,6,0],[82666,4,0],[82933,7,0],[83199,0,0],[83199,7,267]]},{"mustHitSection":true,"typeOfSection":0,"lengthInSteps":16,"sectionNotes":[[83466,0,0],[83733,1,0],[83999,1,0],[84266,3,0]]},{"mustHitSection":true,"typeOfSection":0,"lengthInSteps":16,"sectionNotes":[[84533,3,0],[84799,0,0],[85066,3,0],[85333,7,0]]},{"mustHitSection":false,"typeOfSection":0,"lengthInSteps":16,"sectionNotes":[[85599,0,0],[85866,2,0],[86133,2,0],[86399,0,0]]},{"mustHitSection":true,"typeOfSection":0,"lengthInSteps":16,"sectionNotes":[[86666,7,0],[86933,5,0],[87199,5,0],[87466,3,0],[87466,5,267]]},{"mustHitSection":true,"typeOfSection":0,"lengthInSteps":16,"sectionNotes":[[87733,0,0],[87999,1,0],[88266,2,0],[88533,2,0]]},{"mustHitSection":true,"typeOfSection":0,"lengthInSteps":16,"sectionNotes":[[88799,2,0],[89066,3,0],[89333,2,0],[89599,1,267],[89599,4,0]]},{"mustHitSection":false,"typeOfSection":0,"lengthInSteps":16,"sectionNotes":[[89866,0,0],[90133,3,0],[90399,3,0],[90666,2,0]]},{"mustHitSection":true,"typeOfSection":0,"lengthInSteps":16,"sectionNotes":[[90933,6,0],[91199,4,0],[91466,7,0],[91733,0,0],[91733,7,266]]},{"mustHitSection":true,"typeOfSection":0,"lengthInSteps":16,"sectionNotes":[[91999,0,0],[92266,1,0],[92533,1,0],[92799,3,0]]},{"mustHitSection":true,"typeOfSection":0,"lengthInSteps":16,"sectionNotes":[[93066,3,0],[93333,0,0],[93599,3,0],[93866,1,267]]}]}}